agentic/__init__.py
agentic/server.py
agentic/a2a/__init__.py
agentic/a2a/client.py
agentic/a2a/core.py
agentic/a2a/server.py
agentic/a2a/utility.py
agentic/mcp/__init__.py
agentic/mcp/core.py
agentic/mcp/server.py
agentic_a2a-0.1.13.dist-info/METADATA
agentic_a2a-0.1.13.dist-info/WHEEL
agentic_a2a-0.1.13.dist-info/top_level.txt
agentic_a2a-0.1.13.dist-info/RECORD
