Metadata-Version: 2.4
Name: agentic-a2a
Version: 0.1.13
Summary: Python framework for implementing multi-agent systems
Home-page: https://github.com/DevTurtleBlog/agentic
Author: devturtleblog@gmail.com
Classifier: Programming Language :: Python :: 3
Classifier: License :: OSI Approved :: MIT License
Classifier: Operating System :: OS Independent
Requires-Python: >=3.9
Requires-Dist: uvicorn
Requires-Dist: fastapi
Requires-Dist: a2a-sdk
Requires-Dist: fastapi-mcp
Provides-Extra: dev
Requires-Dist: pytest; extra == "dev"
Requires-Dist: pytest-runner; extra == "dev"
Provides-Extra: test
Requires-Dist: pytest; extra == "test"
Dynamic: author
Dynamic: classifier
Dynamic: description
Dynamic: description-content-type
Dynamic: home-page
Dynamic: provides-extra
Dynamic: requires-dist
Dynamic: requires-python
Dynamic: summary
